setup.py
doxdox/__init__.py
doxdox/doxdox.py
doxdox.egg-info/PKG-INFO
doxdox.egg-info/SOURCES.txt
doxdox.egg-info/dependency_links.txt
doxdox.egg-info/requires.txt
doxdox.egg-info/top_level.txt