Metadata-Version: 1.0
Name: doxdox
Version: 0.1alpha
Summary: A simple documentation generator that takes output from dox and builds a Bootstrap based documentation file.
Home-page: https://github.com/neogeek/doxdox
Author: Scott Doxey
Author-email: UNKNOWN
License: UNKNOWN
Platform: UNKNOWN
